py_pcha/PCHA.py
py_pcha/__init__.py
py_pcha/furthest_sum.py
py_pcha-0.1.3.dist-info/LICENCE
py_pcha-0.1.3.dist-info/METADATA
py_pcha-0.1.3.dist-info/WHEEL
py_pcha-0.1.3.dist-info/top_level.txt
py_pcha-0.1.3.dist-info/RECORD
