Metadata-Version: 2.1
Name: py-pcha
Version: 0.1.3
Summary: Python implemenation of PCHA algorithm for Archetypal Analysis
Home-page: https://github.com/ulfaslak/py_pcha
Author: Ulf Aslak
Author-email: ulfjensen@gmail.com
License: MIT
Keywords: Archetypal Analysis,AA,PCHA,Clustering,Machine Learning,Signal Processing
Platform: UNKNOWN
Classifier: Intended Audience :: Science/Research
Classifier: Programming Language :: Python
Classifier: Programming Language :: Python :: 3
Classifier: Programming Language :: Python :: 3.7
Classifier: Topic :: Scientific/Engineering :: Information Analysis
Classifier: Topic :: Scientific/Engineering :: Mathematics
